pdm_sbom-0.9.2.dist-info/METADATA
pdm_sbom-0.9.2.dist-info/WHEEL
pdm_sbom-0.9.2.dist-info/entry_points.txt
pdm_sbom-0.9.2.dist-info/licenses/LICENSE
pdm_sbom/__init__.py
pdm_sbom/cli.py
pdm_sbom/core/__init__.py
pdm_sbom/core/abstractions.py
pdm_sbom/core/compat.py
pdm_sbom/dag/__init__.py
pdm_sbom/dag/builder.py
pdm_sbom/dag/graph.py
pdm_sbom/plugin.py
pdm_sbom/project/__init__.py
pdm_sbom/project/builder.py
pdm_sbom/project/dataclasses.py
pdm_sbom/project/reader.py
pdm_sbom/project/tools.py
pdm_sbom/sbom/__init__.py
pdm_sbom/sbom/base.py
pdm_sbom/sbom/buildinfo.py
pdm_sbom/sbom/cyclonedx.py
pdm_sbom/sbom/json.py
pdm_sbom/sbom/spdx.py
pdm_sbom/sbom/spdx3.py
pdm_sbom-0.9.2.dist-info/RECORD
