Metadata-Version: 2.1
Name: pdm-sbom
Version: 0.9.2
Summary: Generate Software Bill of Materials from PDM based projects
Home-page: https://github.com/carstencodes/pdm-sbom
Author-Email: Carsten Igel <cig@bite-that-bit.de>
License: MIT
Project-URL: Homepage, https://github.com/carstencodes/pdm-sbom
Requires-Python: >=3.11
Requires-Dist: pdm>=2.3.4
Requires-Dist: pyproject-metadata>=0.6.1
Requires-Dist: resolvelib>=0.9.0
Requires-Dist: packaging>=21.3
Requires-Dist: pdm-pfsc>=0.11.3
Requires-Dist: packageurl-python>=0.15.0
Requires-Dist: cyclonedx-bom>=3.10.1; extra == "cyclonedx"
Requires-Dist: spdx-tools>=0.7.0; extra == "spdx"
Requires-Dist: buildinfo-om>=0.6.0; extra == "buildinfo"
Requires-Dist: spdx-tools>=0.8.2; extra == "spdx3"
Requires-Dist: pyshacl>=0.25.0; extra == "spdx3"
Requires-Dist: semantic-version>=2.10.0; extra == "spdx3"
Provides-Extra: cyclonedx
Provides-Extra: spdx
Provides-Extra: buildinfo
Provides-Extra: spdx3
